{
  "pins": {
    "mnw": {
      "type": "Git",
      "repository": {
        "type": "GitHub",
        "owner": "Gerg-L",
        "repo": "mnw"
      },
      "branch": "master",
      "submodules": false,
      "revision": "cfbc7d1cc832e318d0863a5fc91d940a96034001",
      "url": "https://github.com/Gerg-L/mnw/archive/cfbc7d1cc832e318d0863a5fc91d940a96034001.tar.gz",
      "hash": "0s369nzhlxnzj82l64nxi711a8kaibzikmlxrbcsigbwh5ijzck3"
    },
    "nixpkgs": {
      "type": "Channel",
      "name": "nixpkgs-unstable",
      "url": "https://releases.nixos.org/nixpkgs/nixpkgs-25.11pre871443.d7f52a7a640b/nixexprs.tar.xz",
      "hash": "1wxjmwn2dsrq9ap3h38b2xn2w60pijgkg2fqg86xhjf48fdnsg68"
    }
  },
  "version": 5
}
